MANIFEST.in
README.md
setup.py
NEMO_transaction_validation/__init__.py
NEMO_transaction_validation/admin.py
NEMO_transaction_validation/models.py
NEMO_transaction_validation/urls.py
NEMO_transaction_validation/views.py
NEMO_transaction_validation.egg-info/PKG-INFO
NEMO_transaction_validation.egg-info/SOURCES.txt
NEMO_transaction_validation.egg-info/dependency_links.txt
NEMO_transaction_validation.egg-info/top_level.txt
NEMO_transaction_validation/management/__init__.py
NEMO_transaction_validation/management/commands/__init__.py
NEMO_transaction_validation/management/commands/auto_validate_transactions.py
NEMO_transaction_validation/migrations/0001_NEMO_transaction_validation_0_0_1.py
NEMO_transaction_validation/migrations/0002_auto_20210730_1125.py
NEMO_transaction_validation/migrations/__init__.py
NEMO_transaction_validation/templates/transaction_validation/contest.html
NEMO_transaction_validation/templates/transaction_validation/contest_staff_charge.html
NEMO_transaction_validation/templates/transaction_validation/contest_usage_event.html
NEMO_transaction_validation/templates/transaction_validation/landing_custom.html
NEMO_transaction_validation/templates/transaction_validation/review_aar_contests.html
NEMO_transaction_validation/templates/transaction_validation/review_contests.html
NEMO_transaction_validation/templates/transaction_validation/review_sc_contests.html
NEMO_transaction_validation/templates/transaction_validation/review_ue_contests.html
NEMO_transaction_validation/templates/transaction_validation/validation.html