Metadata-Version: 2.1
Name: NEMO-transaction-validation
Version: 0.2.10
Summary: NEMO Plugin - Transaction Validation
Home-page: UNKNOWN
License: UNKNOWN
Platform: UNKNOWN
